MANIFEST.in
RELEASE-VERSION
pavement.py
paver-minilib.zip
setup.py
version.py
barcode_scanner/__init__.py
barcode_scanner/__main__.py
barcode_scanner/canvas.py
barcode_scanner/gtk_matplotlib.py
barcode_scanner/io_redirect.py
barcode_scanner/scanner.py
barcode_scanner.egg-info/PKG-INFO
barcode_scanner.egg-info/SOURCES.txt
barcode_scanner.egg-info/dependency_links.txt
barcode_scanner.egg-info/pbr.json
barcode_scanner.egg-info/requires.txt
barcode_scanner.egg-info/top_level.txt
barcode_scanner/bin/__init__.py
barcode_scanner/bin/main.py