Metadata-Version: 1.0
Name: barcode-scanner
Version: 0.2.post16
Summary: Barcode scanner based on GStreamer, zbar, and gtk.
Home-page: https://github.com/wheeler-microfluidics/barcode-scanner
Author: Christian Fobel and Michael D. M. Dryden
Author-email: christian@fobel.net and mdryden@chem.utoronto.ca
License: GPL
Keywords: gtk,zbar,gstreamer
Platform: UNKNOWN
